{
    "phase":  "project-docs-audit",
    "timestamp":  "2026-03-11T15:07:03",
    "files":  [
                  "PROJECT_TREE.md",
                  "PROJECT_ROUTES.md",
                  "PROJECT_OWNERSHIP.md"
              ],
    "generators":  [
                       "tools/generate-project-tree.js",
                       "tools/generate-project-routes.js",
                       "tools/generate-project-ownership.js"
                   ],
    "route_file_count":  95,
    "ownership_sections":  72,
    "tree_file_entries":  1767
}